streamlit_pydantic_form/__init__.py
streamlit_pydantic_form/_exceptions.py
streamlit_pydantic_form/_form.py
streamlit_pydantic_form/py.typed
streamlit_pydantic_form/widget.py
streamlit_pydantic_form-0.0.6.dist-info/LICENSE
streamlit_pydantic_form-0.0.6.dist-info/METADATA
streamlit_pydantic_form-0.0.6.dist-info/WHEEL
streamlit_pydantic_form-0.0.6.dist-info/RECORD
