Metadata-Version: 2.1
Name: streamlit-pydantic-form
Version: 0.0.6
Summary: Streamlit form component defined by a Pydantic model
Home-page: https://github.com/shunichironomura/streamlit-pydantic-form
License: MIT
Keywords: streamlit,pydantic,form
Author: Shunichiro Nomura
Author-email: nomura@space.t.u-tokyo.ac.jp
Requires-Python: >=3.11
Classifier: Development Status :: 4 - Beta
Classifier: Intended Audience :: Developers
Classifier: License :: OSI Approved :: MIT License
Classifier: Programming Language :: Python :: 3
Classifier: Programming Language :: Python :: 3.11
Classifier: Programming Language :: Python :: 3.12
Requires-Dist: pydantic (>=2.5.3)
Requires-Dist: streamlit (>=1.37.0)
Requires-Dist: typing-extensions (>=4.9.0)
Project-URL: Repository, https://github.com/shunichironomura/streamlit-pydantic-form
